ensenso_nxlib/__init__.py
nxlib/__init__.py
nxlib/_helper.py
nxlib/api.py
nxlib/command.py
nxlib/constants.py
nxlib/context.py
nxlib/exception.py
nxlib/item.py
nxlib/log.py
ensenso_nxlib-4.3.880.dist-info/LICENSE.md
ensenso_nxlib-4.3.880.dist-info/LICENSE.md.in
ensenso_nxlib-4.3.880.dist-info/METADATA
ensenso_nxlib-4.3.880.dist-info/WHEEL
ensenso_nxlib-4.3.880.dist-info/top_level.txt
ensenso_nxlib-4.3.880.dist-info/RECORD
